asciiquarium/__init__.py
asciiquarium/__version__.py
asciiquarium/animation.py
asciiquarium/entity.py
asciiquarium/main.py
asciiquarium/version_checker.py
asciiquarium/entities/__init__.py
asciiquarium/entities/environment.py
asciiquarium/entities/fish.py
asciiquarium/entities/special.py
asciiquarium-2.2.0.dist-info/METADATA
asciiquarium-2.2.0.dist-info/WHEEL
asciiquarium-2.2.0.dist-info/entry_points.txt
asciiquarium-2.2.0.dist-info/licenses/LICENSE
asciiquarium-2.2.0.dist-info/RECORD
