Metadata-Version: 2.4
Name: asciiquarium
Version: 2.2.0
Summary: An aquarium/sea animation in ASCII art for your terminal
Project-URL: Homepage, https://mkabumattar.com/
Project-URL: Repository, https://github.com/MKAbuMattar/asciiquarium-python
Project-URL: Original Project, http://robobunny.com/projects/asciiquarium
Project-URL: Author Website, https://mkabumattar.com/
Author-email: Mohammad Abu Mattar <info@mkabumattar.com>
License-Expression: GPL-3.0-or-later
License-File: LICENSE
Keywords: animation,aquarium,ascii,cli,terminal
Classifier: Development Status :: 4 - Beta
Classifier: Environment :: Console
Classifier: Intended Audience :: End Users/Desktop
Classifier: Operating System :: OS Independent
Classifier: Programming Language :: Python :: 3
Classifier: Programming Language :: Python :: 3.8
Classifier: Programming Language :: Python :: 3.9
Classifier: Programming Language :: Python :: 3.10
Classifier: Programming Language :: Python :: 3.11
Classifier: Programming Language :: Python :: 3.12
Classifier: Programming Language :: Python :: 3.13
Classifier: Programming Language :: Python :: 3.14
Classifier: Topic :: Games/Entertainment
Requires-Python: >=3.8
Requires-Dist: windows-curses>=2.4.1; sys_platform == 'win32' and python_version < '3.13'
Provides-Extra: dev
Requires-Dist: black>=22.0.0; extra == 'dev'
Requires-Dist: hatch>=1.8.0; extra == 'dev'
Requires-Dist: isort>=5.10.0; extra == 'dev'
Requires-Dist: mypy>=1.0.0; extra == 'dev'
Requires-Dist: pytest>=7.0.0; extra == 'dev'
Requires-Dist: ruff>=0.1.0; extra == 'dev'
